setup.py
shinchan/__init__.py
shinchan/email_client.py
shinchan/logger.py
shinchan/mongo_client.py
shinchan/monitor.py
shinchan.egg-info/PKG-INFO
shinchan.egg-info/SOURCES.txt
shinchan.egg-info/dependency_links.txt
shinchan.egg-info/top_level.txt
shinchan/helper/__init__.py
shinchan/helper/daemon.py
shinchan/helper/helper.py