Metadata-Version: 1.0
Name: shinchan
Version: 0.0.1
Summary: Logging and notification utility in python
Home-page: https://github.com/asamat/shinchan
Author: Arunim Samat
Author-email: arunimsamat@gmail.com
License: MIT License
Platform: UNKNOWN
